sleps/__init__.py
sleps/utils.py
sleps/version.py
sleps/eclusters/__init__.py
sleps/eclusters/base.py
sleps/eclusters/cluster.py
sleps/eclusters/embedding.py
sleps-0.0.0.dist-info/LICENSE
sleps-0.0.0.dist-info/METADATA
sleps-0.0.0.dist-info/WHEEL
sleps-0.0.0.dist-info/top_level.txt
sleps-0.0.0.dist-info/RECORD
