Metadata-Version: 2.1
Name: sleps
Version: 0.0.0
Summary: Some Pipelines
License: MIT License
Requires-Python: >=3.8
License-File: LICENSE
Requires-Dist: numpy ==1.26.4
Requires-Dist: pandas ==2.2.2
Requires-Dist: gensim ==4.3.2
Requires-Dist: psutil ==5.9.5
Requires-Dist: scikit-learn ==1.3.2
Requires-Dist: scipy ==1.11.3
Requires-Dist: sentence-transformers ==2.3.1
Requires-Dist: tqdm ==4.66.4
Requires-Dist: umap-learn ==0.5.6
